<?xml version="1.0" encoding="utf-8" standalone="yes" ?>
<pie_menu name="Self Pie">
	<menu_item_call label="档案..." name="Profile..." />
	<menu_item_call label="社团" name="Groups" />
	<menu_item_call label="前往..." name="Go..." />
	<menu_item_call label="起身" name="Stand Up" />
	<menu_item_call label="好友" name="Friends" />
	<menu_item_call label="动作..." name="Gestures..." />
	<pie_menu label="脱下 &gt;" name="Take Off &gt;">
		<pie_menu label="服饰 &gt;" name="Clothes &gt;">
			<menu_item_call label="衬衣" name="Shirt" />
			<menu_item_call label="裤子" name="Pants" />
			<menu_item_call label="鞋子" name="Shoes" />
			<menu_item_call label="袜子" name="Socks" />
			<menu_item_call label="夹克" name="Jacket" />
			<menu_item_call label="手套" name="Gloves" />
			<pie_menu label="更多 &gt;" name="More &gt;">
				<menu_item_call label="内衣" name="Self Undershirt" />
				<menu_item_call label="透明度蒙板" name="Self Alpha" />
				<menu_item_call label="所有服饰" name="All Clothes" />
				<menu_item_call label="纹身" name="Self Tattoo" />
				<menu_item_call label="内裤" name="Self Underpants" />
			</pie_menu>
			<menu_item_call label="裙子" name="Skirt" />
		</pie_menu>
		<pie_menu label="HUD &gt;" name="Object Detach HUD" />
		<pie_menu label="卸下 &gt;" name="Object Detach" />
		<menu_item_call label="分开全部" name="Detach All" />
	</pie_menu>
	<menu_item_call label="外观..." name="Appearance..." />
</pie_menu>
