<llsd>
  <array>

    <!--
        This file contains fallback settings only.
        The actual list of grids is loaded from a web server.
    -->

    <map>
      <key>default_grids_version</key><string>0</string>
    </map>

    <!-- Local Host -->
    <map>
      <key>gridnick</key><string>localhost</string>
      <key>gridname</key><string>Local Host</string>
      <key>platform</key><string>OpenSim</string>
      <key>loginuri</key><string>http://127.0.0.1:9000/</string>
      <key>helperuri</key><string>http://127.0.0.1:9000/</string>
    </map>

  </array>
</llsd>
