<?xml version="1.0" encoding="ISO-8859-1" standalone="yes"?>
<pie_menu name="Land Pie"><menu_item_call enabled="false" hidden="false" label="Sobre o terreno..." mouse_opaque="true"	     name="About Land..."><on_click function="ShowFloater" userdata="about land" />
</menu_item_call>
<menu_item_call enabled="false" hidden="false" label="Criar" mouse_opaque="true" name="Create"><on_click function="Land.Build" />
<on_enable function="EnableEdit" />
</menu_item_call>
<menu_item_call enabled="false" hidden="false" label="Ir para" mouse_opaque="true"	     name="Go Here"><on_click function="GoToObject" />
</menu_item_call>
<menu_item_call enabled="false" hidden="false" label="Sentar" mouse_opaque="true"	     name="Sit Here"><on_click function="Land.Sit" />
</menu_item_call>
<menu_item_separator />
<menu_item_call enabled="false" hidden="false" label="Comprar passe..." mouse_opaque="true"	     name="Land Buy Pass"><on_click function="Land.BuyPass" />
<on_enable function="Land.EnableBuyPass" />
</menu_item_call>
<menu_item_call enabled="false" hidden="false" label="Editar terreno" mouse_opaque="true"	     name="Edit Terrain"><on_click function="Land.Edit" />
<on_enable function="EnableEdit" />
</menu_item_call>
<menu_item_call enabled="false" hidden="false" label="Comprar Terras..." mouse_opaque="true"	     name="Land Buy"><on_click function="ShowFloater" userdata="buy land" />
<on_enable function="World.EnableBuyLand" />
</menu_item_call>
</pie_menu>
